LICENSE
MANIFEST.in
README.rst
pyproject.toml
setup.cfg
setup.py
pretix_pridepopup/__init__.py
pretix_pridepopup/apps.py
pretix_pridepopup/forms.py
pretix_pridepopup/signals.py
pretix_pridepopup/urls.py
pretix_pridepopup/views.py
pretix_pridepopup.egg-info/PKG-INFO
pretix_pridepopup.egg-info/SOURCES.txt
pretix_pridepopup.egg-info/dependency_links.txt
pretix_pridepopup.egg-info/entry_points.txt
pretix_pridepopup.egg-info/top_level.txt
pretix_pridepopup/locale/de/LC_MESSAGES/django.po
pretix_pridepopup/locale/de_Informal/.gitkeep
pretix_pridepopup/locale/de_Informal/LC_MESSAGES/django.po
pretix_pridepopup/static/pretix_pridepopup/.gitkeep
pretix_pridepopup/static/pretix_pridepopup/banner-2024.js
pretix_pridepopup/templates/pretix_pridepopup/.gitkeep
pretix_pridepopup/templates/pretix_pridepopup/presale_head.html
pretix_pridepopup/templates/pretix_pridepopup/settings.html
tests/test_main.py