Metadata-Version: 2.4
Name: pretix-pridepopup
Version: 1.0.0
Summary: Display the Pride Pop-up (https://www.accep.lgbt/) on your pretix shop
Author-email: Martin Gross <martin@pc-coholic.de>
Maintainer-email: Martin Gross <martin@pc-coholic.de>
License: Apache
Project-URL: homepage, https://github.com/pc-coholic/pretix-pridepopup/
Project-URL: repository, https://github.com/pc-coholic/pretix-pridepopup/
Keywords: pretix
License-File: LICENSE
Dynamic: license-file
